{"LevelMap": {"LID": 7364973, "Layers": 13, "AnimSpriteLibVersion": 4102, "Version": 4123, "data": [{"Width": 13, "data": [{"data": [{"X": 2, "SID": "grid"}, {"X": 11, "SID": ""}], "GridLine": 2}, {"data": [{"X": 2, "SID": "grid"}, {"X": 11, "SID": ""}], "GridLine": 3}, {"data": [{"X": 3, "SID": "grid"}, {"X": 10, "SID": ""}], "GridLine": 4}, {"data": [{"X": 3, "SID": "grid"}, {"X": 10, "SID": ""}], "GridLine": 5}, {"data": [{"X": 3, "SID": "grid"}, {"X": 10, "SID": ""}], "GridLine": 6}, {"data": [{"X": 3, "SID": "grid"}, {"X": 10, "SID": ""}], "GridLine": 7}, {"data": [{"X": 3, "SID": "grid"}, {"X": 10, "SID": ""}], "GridLine": 8}, {"data": [{"X": 2, "SID": "grid"}, {"X": 11, "SID": ""}], "GridLine": 9}, {"data": [{"X": 2, "SID": "grid"}, {"X": 11, "SID": ""}], "GridLine": 10}], "Name": "background", "Height": 13}, {"Width": 13, "data": [], "Name": "conveyor", "Height": 13}, {"Width": 13, "data": [{"data": [{"X": 2, "SID": "figures_area"}, {"X": 4, "SID": "swirl_5"}, {"X": 5, "SID": "figures_area"}, {"X": 6, "SID": "swirl_5"}, {"X": 7, "SID": "figures_area"}, {"X": 8, "SID": "swirl_5"}, {"X": 9, "SID": "figures_area"}, {"X": 11, "SID": ""}], "GridLine": 2}, {"data": [{"X": 2, "SID": "figures_area"}, {"X": 11, "SID": ""}], "GridLine": 3}, {"data": [{"X": 3, "SID": "figures_force"}, {"X": 4, "SID": "figures_area"}, {"X": 9, "SID": "figures_force"}, {"X": 10, "SID": ""}], "GridLine": 4}, {"data": [{"X": 3, "SID": "figures_area"}, {"X": 10, "SID": ""}], "GridLine": 5}, {"data": [{"X": 3, "SID": "figures_force"}, {"X": 4, "SID": "figures_area"}, {"X": 9, "SID": "figures_force"}, {"X": 10, "SID": ""}], "GridLine": 6}, {"data": [{"X": 3, "SID": "figures_force"}, {"X": 4, "SID": "figures_area"}, {"X": 9, "SID": "figures_force"}, {"X": 10, "SID": ""}], "GridLine": 7}, {"data": [{"X": 3, "SID": "swirl"}, {"X": 4, "SID": "figures_area"}, {"X": 9, "SID": "swirl"}, {"X": 10, "SID": ""}], "GridLine": 8}, {"data": [{"X": 2, "SID": "swirl_5"}, {"X": 3, "SID": "swirl_2"}, {"X": 4, "SID": "figures_area"}, {"X": 5, "SID": "swirl_2"}, {"X": 6, "SID": "figures_area"}, {"X": 7, "SID": "swirl_2"}, {"X": 8, "SID": "figures_area"}, {"X": 9, "SID": "swirl_2"}, {"X": 10, "SID": "swirl_5"}, {"X": 11, "SID": ""}], "GridLine": 9}, {"data": [{"X": 2, "SID": "swirl_5"}, {"X": 3, "SID": "swirl_2"}, {"X": 4, "SID": "swirl_4"}, {"X": 5, "SID": "swirl_3"}, {"X": 8, "SID": "swirl_4"}, {"X": 9, "SID": "swirl_2"}, {"X": 10, "SID": "swirl_5"}, {"X": 11, "SID": ""}], "GridLine": 10}], "Name": "figures", "Height": 13}, {"Width": 13, "data": [{"data": [{"X": 4, "SID": "hbonus_area"}, {"X": 5, "SID": ""}, {"X": 8, "SID": "hbonus_area"}, {"X": 9, "SID": ""}], "GridLine": 5}, {"data": [{"X": 5, "SID": "vbonus_area"}, {"X": 6, "SID": ""}, {"X": 7, "SID": "vbonus_area"}, {"X": 8, "SID": ""}], "GridLine": 6}, {"data": [{"X": 6, "SID": "bomb_area"}, {"X": 7, "SID": ""}], "GridLine": 7}], "Name": "figures_bonus", "Height": 13}, {"Width": 13, "data": [], "Name": "figures_chains", "Height": 13}, {"Width": 13, "data": [{"data": [{"X": 3, "SID": "mystery_piece_holder"}, {"X": 10, "SID": ""}], "GridLine": 2}, {"data": [{"X": 4, "SID": "mystery_piece_holder"}, {"X": 5, "SID": ""}, {"X": 8, "SID": "mystery_piece_holder"}, {"X": 9, "SID": ""}], "GridLine": 5}, {"data": [{"X": 5, "SID": "mystery_piece_holder"}, {"X": 6, "SID": ""}, {"X": 7, "SID": "mystery_piece_holder"}, {"X": 8, "SID": ""}], "GridLine": 6}, {"data": [{"X": 6, "SID": "mystery_piece_holder"}, {"X": 7, "SID": ""}], "GridLine": 7}], "Name": "mystery", "Height": 13}, {"Width": 13, "data": [], "Name": "milk", "Height": 13}, {"Width": 13, "data": [], "Name": "dont_mix_items", "Height": 13}, {"Width": 13, "data": [{"data": [{"X": 3, "SID": "relic"}, {"X": 4, "SID": ""}, {"X": 5, "SID": "relic"}, {"X": 6, "SID": ""}, {"X": 7, "SID": "relic"}, {"X": 8, "SID": ""}, {"X": 9, "SID": "relic"}, {"X": 10, "SID": ""}], "GridLine": 2}], "Name": "relic_area", "Height": 13}, {"Width": 13, "data": [{"data": [{"X": 2, "SID": "grid"}, {"X": 11, "SID": ""}], "GridLine": 10}], "Name": "pickup", "Height": 13}, {"Width": 13, "data": [], "Name": "teleports", "Height": 13}, {"Width": 13, "data": [{"data": [{"X": 2, "SID": "grid"}, {"X": 11, "SID": ""}], "GridLine": 2}], "Name": "generators", "Height": 13}, {"Width": 13, "data": [], "Name": "portals", "Height": 13}]}, "MapView": {"Flags": 0, "SelColor": 65280, "GridColor": 12632256, "BkColor": -7500403, "Grid": true, "LayerMode": 2}, "TileView": {"Scale": 1, "GridColor": 12632256, "BkColor": -8750470}, "CustomProps": {"NumProps": 26, "data": [{"DocID": "Add_Boots_Every_Generation", "PropVal": "0"}, {"DocID": "Chapter_ID", "PropVal": "16"}, {"DocID": "Color_Ratio_1", "PropVal": "1.000000"}, {"DocID": "Color_Ratio_2", "PropVal": "1.050000"}, {"DocID": "Color_Ratio_3", "PropVal": "1.100000"}, {"DocID": "Color_Ratio_4", "PropVal": "0.920000"}, {"DocID": "Color_Ratio_5", "PropVal": "0.970000"}, {"DocID": "Color_Ratio_6", "PropVal": "0.000000"}, {"DocID": "Description", "PropVal": "Level 316"}, {"DocID": "Difficulty", "PropVal": "Medium 2"}, {"DocID": "Dont_Move_Generators", "PropVal": "true"}, {"DocID": "Drop_Down_Relics", "PropVal": "4"}, {"DocID": "Level", "PropVal": "316"}, {"DocID": "Level_Type", "PropVal": "2"}, {"DocID": "Level_Type_1", "PropVal": "0"}, {"DocID": "Level_Type_2", "PropVal": "0"}, {"DocID": "Moves_To_First_Relic", "PropVal": "0"}, {"DocID": "Moves_To_Next_Relic", "PropVal": "0"}, {"DocID": "Need_Clear", "PropVal": "false"}, {"DocID": "Need_Way", "PropVal": "false"}, {"DocID": "No_Start_Bonuses", "PropVal": "true"}, {"DocID": "Num_Moves", "PropVal": "30"}, {"DocID": "Score_2", "PropVal": "71900"}, {"DocID": "Score_3", "PropVal": "96200"}, {"DocID": "Start_Drop_Down_Relics", "PropVal": "4"}, {"DocID": "Way_Relic", "PropVal": "false"}]}, "CustomDocProps": {"SampleBankFileName": "", "LocaleFileName": "", "data": [{"PropType": 1, "PropName": "Add_Boots_Every_Generation"}, {"PropType": 1, "PropName": "Chapter_ID"}, {"PropType": 2, "PropName": "Color_Ratio_1"}, {"PropType": 2, "PropName": "Color_Ratio_2"}, {"PropType": 2, "PropName": "Color_Ratio_3"}, {"PropType": 2, "PropName": "Color_Ratio_4"}, {"PropType": 2, "PropName": "Color_Ratio_5"}, {"PropType": 2, "PropName": "Color_Ratio_6"}, {"PropType": 0, "PropName": "Description"}, {"PropType": 0, "PropName": "Difficulty"}, {"PropType": 3, "PropName": "Dont_Move_Generators"}, {"PropType": 1, "PropName": "Drop_Down_Relics"}, {"PropType": 310, "PropName": "Level"}, {"PropType": 1, "PropName": "Level_Type"}, {"PropType": 1, "PropName": "Level_Type_1"}, {"PropType": 1, "PropName": "Level_Type_2"}, {"PropType": 1, "PropName": "Moves_To_First_Relic"}, {"PropType": 1, "PropName": "Moves_To_Next_Relic"}, {"PropType": 3, "PropName": "Need_Clear"}, {"PropType": 3, "PropName": "Need_Way"}, {"PropType": 3, "PropName": "No_Start_Bonuses"}, {"PropType": 1, "PropName": "Num_Moves"}, {"PropType": 1, "PropName": "Score_2"}, {"PropType": 1, "PropName": "Score_3"}, {"PropType": 1, "PropName": "Start_Drop_Down_Relics"}, {"PropType": 3, "PropName": "Way_Relic"}], "NumDocProps": 26}}